[
  {
    "length": "Short (1:04)",
    "popularity": "High (309K)",
    "channel_size": "Small (94 - Ramon Alcantara)",
    "url": "https://www.youtube.com/watch?v=S5xW3eigjew"
  },
  {
    "length": "Short (2:59)",
    "popularity": "High (146k)",
    "channel_size": "Large (116K - Lisa Remillard)",
    "url": "https://www.youtube.com/watch?v=0e4I7sQXxsQ"
  },
  {
    "length": "Short (4:48)",
    "popularity": "High (4.4M)",
    "channel_size": "Medium (17.3K - Aaron)",
    "url": "https://www.youtube.com/watch?v=7_LPdttKXPc"
  },
  {
    "length": "short (1:27)",
    "popularity": "Medium (34k)",
    "channel_size": "Medium (84.2k - RAPGAME)",
    "url": "https://www.youtube.com/watch?v=uvYCVjhuot8"
  },
  {
    "length": "Short (3:55)",
    "popularity": "Low (1.8K)",
    "channel_size": "Medium (17.3K - Aaron)",
    "url": "https://www.youtube.com/watch?v=OIHmV6Ai9eE"
  },
  {
    "length": "short (3:57)",
    "popularity": "Low (419)",
    "channel_size": "Medium - (11.4k - Matt Nye)",
    "url": "https://www.youtube.com/watch?v=AsZeXwbSNLI"
  },
  {
    "length": "short (4:46)",
    "popularity": "Low (626)",
    "channel_size": "Small (398 - Looking for one piece)",
    "url": "https://www.youtube.com/watch?v=DPn2-ce8wP0"
  },
  {
    "length": "Short (0:56)",
    "popularity": "Low (875)",
    "channel_size": "Large - (117K - UNITED States Air Force)",
    "url": "https://www.youtube.com/watch?v=Pfh9l0guTqQ"
  }
]
  